stormlight/__init__.py
stormlight/analysis.py
stormlight/datasets.py
stormlight/modeling.py
stormlight/processing.py
stormlight/utils.py
stormlight-0.1.1.dist-info/DESCRIPTION.rst
stormlight-0.1.1.dist-info/METADATA
stormlight-0.1.1.dist-info/RECORD
stormlight-0.1.1.dist-info/WHEEL
stormlight-0.1.1.dist-info/metadata.json
stormlight-0.1.1.dist-info/top_level.txt
