Metadata-Version: 2.0
Name: stormlight
Version: 0.1.1
Summary: NLP project based on The Stormlight Archive by Brandon Sanderson.
Home-page: UNKNOWN
Author: Harrison Mamin
Author-email: harrisonmamin@gmail.com
License: UNKNOWN
Platform: UNKNOWN
Requires-Dist: htools
Requires-Dist: nltk
Requires-Dist: numpy (==1.17.4)
Requires-Dist: pandas (==0.25.3)
Requires-Dist: textblob
Requires-Dist: torch
Requires-Dist: transformers
Requires-Dist: vaderSentiment
